procela/__init__.py
procela-0.0.0.dist-info/METADATA
procela-0.0.0.dist-info/WHEEL
procela-0.0.0.dist-info/top_level.txt
procela-0.0.0.dist-info/RECORD
